<annotation>
	<folder/>
	<filename>MOXA_332.jpg</filename>
	<path>../../dataset/moxa3K/train//MOXA_332.jpg</path>
	<source>
		<database>Moxa3k</database>
	</source>
	<size>
		<width>900</width>
		<height>700</height>
		<depth>3</depth>
	</size>
	<segmented>0</segmented>
	<object>
		<name>mask</name>
		<pose>Unspecified</pose>
		<truncated>0</truncated>
		<difficult>0</difficult>
		<bndbox>
			<xmin>157</xmin>
			<ymin>322</ymin>
			<xmax>234</xmax>
			<ymax>398</ymax>
		</bndbox>
	</object>
	<object>
		<name>mask</name>
		<pose>Unspecified</pose>
		<truncated>0</truncated>
		<difficult>0</difficult>
		<bndbox>
			<xmin>462</xmin>
			<ymin>27</ymin>
			<xmax>554</xmax>
			<ymax>136</ymax>
		</bndbox>
	</object>
</annotation>
