<annotation>
	<folder/>
	<filename>MOXA_323.jpg</filename>
	<path>../../dataset/moxa3K/train//MOXA_323.jpg</path>
	<source>
		<database>Moxa3k</database>
	</source>
	<size>
		<width>900</width>
		<height>600</height>
		<depth>3</depth>
	</size>
	<segmented>0</segmented>
	<object>
		<name>mask</name>
		<pose>Unspecified</pose>
		<truncated>0</truncated>
		<difficult>0</difficult>
		<bndbox>
			<xmin>381</xmin>
			<ymin>26</ymin>
			<xmax>443</xmax>
			<ymax>123</ymax>
		</bndbox>
	</object>
	<object>
		<name>nomask</name>
		<pose>Unspecified</pose>
		<truncated>0</truncated>
		<difficult>0</difficult>
		<bndbox>
			<xmin>201</xmin>
			<ymin>99</ymin>
			<xmax>255</xmax>
			<ymax>167</ymax>
		</bndbox>
	</object>
	<object>
		<name>nomask</name>
		<pose>Unspecified</pose>
		<truncated>0</truncated>
		<difficult>0</difficult>
		<bndbox>
			<xmin>100</xmin>
			<ymin>165</ymin>
			<xmax>136</xmax>
			<ymax>218</ymax>
		</bndbox>
	</object>
	<object>
		<name>mask</name>
		<pose>Unspecified</pose>
		<truncated>0</truncated>
		<difficult>0</difficult>
		<bndbox>
			<xmin>844</xmin>
			<ymin>25</ymin>
			<xmax>882</xmax>
			<ymax>118</ymax>
		</bndbox>
	</object>
	<object>
		<name>nomask</name>
		<pose>Unspecified</pose>
		<truncated>0</truncated>
		<difficult>0</difficult>
		<bndbox>
			<xmin>733</xmin>
			<ymin>105</ymin>
			<xmax>783</xmax>
			<ymax>173</ymax>
		</bndbox>
	</object>
	<object>
		<name>nomask</name>
		<pose>Unspecified</pose>
		<truncated>0</truncated>
		<difficult>0</difficult>
		<bndbox>
			<xmin>91</xmin>
			<ymin>110</ymin>
			<xmax>146</xmax>
			<ymax>159</ymax>
		</bndbox>
	</object>
</annotation>
