<annotation>
	<folder/>
	<filename>MOXA_904.jpg</filename>
	<path>../../dataset/moxa3K/train//MOXA_904.jpg</path>
	<source>
		<database>Moxa3k</database>
	</source>
	<size>
		<width>2250</width>
		<height>3000</height>
		<depth>3</depth>
	</size>
	<segmented>0</segmented>
	<object>
		<name>mask</name>
		<pose>Unspecified</pose>
		<truncated>0</truncated>
		<difficult>0</difficult>
		<bndbox>
			<xmin>343</xmin>
			<ymin>851</ymin>
			<xmax>574</xmax>
			<ymax>1141</ymax>
		</bndbox>
	</object>
	<object>
		<name>mask</name>
		<pose>Unspecified</pose>
		<truncated>0</truncated>
		<difficult>0</difficult>
		<bndbox>
			<xmin>1164</xmin>
			<ymin>1189</ymin>
			<xmax>1364</xmax>
			<ymax>1462</ymax>
		</bndbox>
	</object>
	<object>
		<name>mask</name>
		<pose>Unspecified</pose>
		<truncated>0</truncated>
		<difficult>0</difficult>
		<bndbox>
			<xmin>1416</xmin>
			<ymin>798</ymin>
			<xmax>1626</xmax>
			<ymax>1056</ymax>
		</bndbox>
	</object>
</annotation>
